{
    "version": "0.3.0",
    "word": "差別",
    "jlpt_level": 3,
    "youtube_link": "https://youtu.be/12VLk6-tYTw",
    "in_db": true,
    "kanji": "差別",
    "reading": "さべつ",
    "introduction_japanese": "差別はニュースや学校の授業でよく出る言葉です。社会の問題や人の権利について話すときに使います。",
    "introduction_english": "さべつ appears often in news and school lessons. We use it when talking about social issues and people’s rights.",
    "meanings": [
        [
            "discrimination",
            "prejudice",
            "bias",
            "segregation",
            "inequity"
        ],
        [
            "distinction",
            "differentiation",
            "classification"
        ]
    ],
    "meaning_explanation_japanese": "人や集団に対して不公平に扱ったり、あるものと別のものの間に違いをつけたりすることを表します。",
    "meaning_explanation_english": "It is a noun and a suru-verb (often used as さべつする). It literally means treating people unfairly or setting differences between groups or things.",
    "youtube_description": "Learn the meaning and usage of さべつ: clear examples, common collocations, and how to talk about discrimination and distinction in natural Japanese.",
    "kanji_details": [
        {
            "kanji": "差",
            "onyomi": [
                "サ"
            ],
            "kunyomi": [
                ""
            ],
            "meanings_english": [
                "difference",
                "gap"
            ],
            "common_words": [
                "差 : さ : difference",
                "差額 : さがく : price difference"
            ]
        },
        {
            "kanji": "別",
            "onyomi": [
                "ベツ"
            ],
            "kunyomi": [
                "わか-れる"
            ],
            "meanings_english": [
                "separate",
                "another"
            ],
            "common_words": [
                "別々 : べつべつ : separately",
                "区別 : くべつ : distinction"
            ]
        }
    ],
    "kanji_explanation": "The first kanji means a difference or a gap. It shows the idea of comparing two or more things. You see it in さ and さがく. Think of noticing how two numbers or prices are not the same. The second kanji means to separate or another. It often appears when we speak about keeping things apart or telling them apart. You see it in べつべつ and くべつ. It carries the feeling of making a line between two sides.",
    "synonyms": [
        "偏見 : へんけん : prejudice",
        "区別 : くべつ : distinction"
    ],
    "synonym_explanation": "The most common synonyms of the word are へんけん and くべつ. へんけん focuses on negative bias in one’s mind, while くべつ is a neutral sorting or distinguishing. さべつ overlaps with both when the distinction becomes unfair treatment.",
    "antonyms": [
        "平等 : びょうどう : equality",
        "公平 : こうへい : fairness"
    ],
    "antonym_explanation": "The most common antonyms of the word are びょうどう and こうへい. They emphasize equal or fair treatment, the opposite of treating people differently in an unfair way.",
    "collocations": [
        {
            "kanji": "1) 人種差別",
            "furigana": "1) 人種(じんしゅ)差別(さべつ)",
            "translations": {
                "EN": "1) Racism",
                "ID": "1) Rasisme",
                "ES": "1) Racismo",
                "VI": "1) Phân biệt chủng tộc",
                "FR": "1) Racisme",
                "NE": "१) जातिवाद",
                "BN": "১) বর্ণবাদ",
                "ZH": "1）种族主义",
                "KO": "1) 인종차별",
                "TL": "1) Rasismo",
                "MY": "၁) လူမျိုးရေးခွဲခြားမှု",
                "HI": "1) नस्लवाद",
                "AR": "1) العنصرية",
                "FA": "۱) نژادپرستی"
            }
        },
        {
            "kanji": "1) 性差別",
            "furigana": "1) 性(せい)差別(さべつ)",
            "translations": {
                "EN": "1) Sex discrimination",
                "ID": "1) Diskriminasi jenis kelamin",
                "ES": "1) Discriminación sexual",
                "VI": "1) Phân biệt đối xử về giới tính",
                "FR": "1) Discrimination sexuelle",
                "NE": "१) लिङ्ग भेदभाव",
                "BN": "১) লিঙ্গ বৈষম্য",
                "ZH": "1）性别歧视",
                "KO": "1) 성차별",
                "TL": "1) Diskriminasyon sa kasarian",
                "MY": "၁) လိင်ခွဲခြားဆက်ဆံခြင်း။",
                "HI": "1) लिंग भेदभाव",
                "AR": "1) التمييز على أساس الجنس",
                "FA": "۱) تبعیض جنسیتی"
            }
        },
        {
            "kanji": "1) 差別問題",
            "furigana": "1) 差別(さべつ)問題(もんだい)",
            "translations": {
                "EN": "1) Discrimination issue",
                "ID": "1) Masalah diskriminasi",
                "ES": "1) Problema de discriminación",
                "VI": "1) Vấn đề phân biệt đối xử",
                "FR": "1) Problème de discrimination",
                "NE": "१) भेदभावको मुद्दा",
                "BN": "১) বৈষম্যের সমস্যা",
                "ZH": "1）歧视问题",
                "KO": "1) 차별 문제",
                "TL": "1) Isyu sa diskriminasyon",
                "MY": "1) ခွဲခြားဆက်ဆံမှုပြဿနာ",
                "HI": "1) भेदभाव का मुद्दा",
                "AR": "1) قضية التمييز",
                "FA": "۱) مسئله تبعیض"
            }
        },
        {
            "kanji": "1) 差別発言",
            "furigana": "1) 差別(さべつ)発言(はつげん)",
            "translations": {
                "EN": "1) Discriminatory remarks",
                "ID": "1) Pernyataan diskriminatif",
                "ES": "1) Comentarios discriminatorios",
                "VI": "1) Nhận xét phân biệt đối xử",
                "FR": "1) Remarques discriminatoires",
                "NE": "१) भेदभावपूर्ण टिप्पणीहरू",
                "BN": "১) বৈষম্যমূলক মন্তব্য",
                "ZH": "1）歧视性言论",
                "KO": "1) 차별 발언",
                "TL": "1) Mga diskriminasyong pananalita",
                "MY": "၁) ခွဲခြားဆက်ဆံသော မှတ်ချက်များ",
                "HI": "1) भेदभावपूर्ण टिप्पणियाँ",
                "AR": "1) التعليقات التمييزية",
                "FA": "۱) اظهارات تبعیض‌آمیز"
            }
        },
        {
            "kanji": "1) 差別の被害",
            "furigana": "1) 差別(さべつ)の被害(ひがい)",
            "translations": {
                "EN": "1) Victims of discrimination",
                "ID": "1) Korban diskriminasi",
                "ES": "1) Víctimas de discriminación",
                "VI": "1) Nạn nhân của sự phân biệt đối xử",
                "FR": "1) Victimes de discrimination",
                "NE": "१) भेदभावका पीडितहरू",
                "BN": "১) বৈষম্যের শিকার",
                "ZH": "1）歧视的受害者",
                "KO": "1) 차별 피해",
                "TL": "1) Mga biktima ng diskriminasyon",
                "MY": "၁) ခွဲခြားဆက်ဆံခံရသူ",
                "HI": "1) भेदभाव के शिकार",
                "AR": "1) ضحايا التمييز",
                "FA": "۱) قربانیان تبعیض"
            }
        },
        {
            "kanji": "1) 差別への対策",
            "furigana": "1) 差別(さべつ)への対策(たいさく)",
            "translations": {
                "EN": "1) Measures against discrimination",
                "ID": "1) Langkah-langkah melawan diskriminasi",
                "ES": "1) Medidas contra la discriminación",
                "VI": "1) Các biện pháp chống phân biệt đối xử",
                "FR": "1) Mesures contre la discrimination",
                "NE": "१) भेदभाव विरुद्धका उपायहरू",
                "BN": "১) বৈষম্যের বিরুদ্ধে ব্যবস্থা",
                "ZH": "1）反歧视措施",
                "KO": "1) 차별에 대한 대책",
                "TL": "1) Mga hakbang laban sa diskriminasyon",
                "MY": "၁) ခွဲခြားဆက်ဆံမှု ဆန့်ကျင်ရေး ဆောင်ရွက်မှု",
                "HI": "1) भेदभाव के विरुद्ध उपाय",
                "AR": "1) التدابير ضد التمييز",
                "FA": "۱) اقدامات علیه تبعیض"
            }
        },
        {
            "kanji": "2) 差別を受ける",
            "furigana": "2) 差別(さべつ)を受(う)ける",
            "translations": {
                "EN": "2) Being discriminated against",
                "ID": "2) Didiskriminasi",
                "ES": "2) Ser discriminado",
                "VI": "2) Bị phân biệt đối xử",
                "FR": "2) Être victime de discrimination",
                "NE": "२) भेदभाव गरिएको",
                "BN": "২) বৈষম্যের শিকার হওয়া",
                "ZH": "2）遭受歧视",
                "KO": "2) 차별을 받는",
                "TL": "2) Pagkakaroon ng diskriminasyon",
                "MY": "၂) ခွဲခြားဆက်ဆံခံရခြင်း။",
                "HI": "2) भेदभाव का शिकार होना",
                "AR": "2) التعرض للتمييز",
                "FA": "۲) مورد تبعیض قرار گرفتن"
            }
        },
        {
            "kanji": "2) 差別をなくす",
            "furigana": "2) 差別(さべつ)をなくす",
            "translations": {
                "EN": "2) Eliminate discrimination",
                "ID": "2) Hilangkan diskriminasi",
                "ES": "2) Eliminar la discriminación",
                "VI": "2) Xóa bỏ sự phân biệt đối xử",
                "FR": "2) Éliminer la discrimination",
                "NE": "२) भेदभाव हटाउनुहोस्",
                "BN": "২) বৈষম্য দূর করুন",
                "ZH": "2）消除歧视",
                "KO": "2) 차별 제거",
                "TL": "2) Tanggalin ang diskriminasyon",
                "MY": "2) ခွဲခြားဆက်ဆံမှု ပပျောက်ပါစေ။",
                "HI": "2) भेदभाव को खत्म करें",
                "AR": "2) القضاء على التمييز",
                "FA": "۲) رفع تبعیض"
            }
        }
    ],
    "example_sentences": [
        {
            "kanji": "私は差別を許しません。",
            "furigana": "私(わたし)は差別(さべつ)を許(ゆる)しません。",
            "translations": {
                "EN": "I do not tolerate discrimination.",
                "ID": "Saya tidak menoleransi diskriminasi.",
                "ES": "No tolero la discriminación.",
                "VI": "Tôi không dung thứ cho sự phân biệt đối xử.",
                "FR": "Je ne tolère pas la discrimination.",
                "NE": "म भेदभाव सहन गर्दिन।",
                "BN": "আমি বৈষম্য সহ্য করি না।",
                "ZH": "我不能容忍歧视。",
                "KO": "나는 차별을 용서하지 않는다.",
                "TL": "Hindi ko kinukunsinti ang diskriminasyon.",
                "MY": "ခွဲခြားဆက်ဆံတာကို သည်းမခံပါဘူး။",
                "HI": "मैं भेदभाव बर्दाश्त नहीं करता.",
                "AR": "لا أتحمل التمييز.",
                "FA": "من تبعیض را تحمل نمی‌کنم."
            }
        },
        {
            "kanji": "学校は差別をなくすために学びます。",
            "furigana": "学校(がっこう)は差別(さべつ)をなくすために学(まな)びます。",
            "translations": {
                "EN": "Schools learn to eliminate discrimination.",
                "ID": "Sekolah belajar untuk menghilangkan diskriminasi.",
                "ES": "Las escuelas aprenden a eliminar la discriminación.",
                "VI": "Trường học học cách xóa bỏ sự phân biệt đối xử.",
                "FR": "Les écoles apprennent à éliminer la discrimination.",
                "NE": "विद्यालयहरूले भेदभाव हटाउन सिक्छन्।",
                "BN": "স্কুলগুলি বৈষম্য দূর করতে শেখে।",
                "ZH": "学校要学习消除歧视。",
                "KO": "학교는 차별을 없애기 위해 배웁니다.",
                "TL": "Natututo ang mga paaralan na alisin ang diskriminasyon.",
                "MY": "ကျောင်းများတွင် ခွဲခြားဆက်ဆံမှု ပပျောက်ရန် သင်ယူပါ။",
                "HI": "स्कूल भेदभाव को खत्म करना सीखते हैं।",
                "AR": "تتعلم المدارس كيفية القضاء على التمييز.",
                "FA": "مدارس یاد می‌گیرند که تبعیض را از بین ببرند."
            }
        },
        {
            "kanji": "差別に反対します。",
            "furigana": "差別(さべつ)に反対(はんたい)します。",
            "translations": {
                "EN": "We are against discrimination.",
                "ID": "Kami menentang diskriminasi.",
                "ES": "Estamos en contra de la discriminación.",
                "VI": "Chúng tôi phản đối sự phân biệt đối xử.",
                "FR": "Nous sommes contre la discrimination.",
                "NE": "हामी भेदभावको विरुद्धमा छौं।",
                "BN": "আমরা বৈষম্যের বিরুদ্ধে।",
                "ZH": "我们反对歧视。",
                "KO": "차별에 반대합니다.",
                "TL": "Kami ay laban sa diskriminasyon.",
                "MY": "ကျွန်ုပ်တို့သည် ခွဲခြားဆက်ဆံခြင်းကို ဆန့်ကျင်ပါသည်။",
                "HI": "हम भेदभाव के खिलाफ हैं.",
                "AR": "نحن ضد التمييز .",
                "FA": "ما مخالف تبعیض هستیم."
            }
        },
        {
            "kanji": "この発言は差別的だと思います。",
            "furigana": "この発言(はつげん)は差別的(さべつてき)だと思(おも)います。",
            "translations": {
                "EN": "I think this statement is discriminatory.",
                "ID": "Saya pikir pernyataan ini diskriminatif.",
                "ES": "Creo que esta afirmación es discriminatoria.",
                "VI": "Tôi nghĩ tuyên bố này mang tính phân biệt đối xử.",
                "FR": "Je pense que cette affirmation est discriminatoire.",
                "NE": "मलाई लाग्छ यो कथन भेदभावपूर्ण छ।",
                "BN": "আমি মনে করি এই বক্তব্য বৈষম্যমূলক।",
                "ZH": "我认为这种说法具有歧视性。",
                "KO": "이 발언은 차별적이라고 생각합니다.",
                "TL": "Sa tingin ko ang pahayag na ito ay may diskriminasyon.",
                "MY": "ဒီထုတ်ပြန်ချက်ဟာ ခွဲခြားဆက်ဆံတယ်လို့ ထင်ပါတယ်။",
                "HI": "मैं समझता हूं कि यह बयान भेदभावपूर्ण है।",
                "AR": "أعتقد أن هذا البيان تمييزي.",
                "FA": "به نظر من این بیانیه تبعیض‌آمیز است."
            }
        },
        {
            "kanji": "みんなを差別なく扱います。",
            "furigana": "みんなを差別(さべつ)なく扱(あつか)います。",
            "translations": {
                "EN": "Treat everyone without discrimination.",
                "ID": "Perlakukan semua orang tanpa diskriminasi.",
                "ES": "Trata a todos sin discriminación.",
                "VI": "Đối xử với mọi người mà không phân biệt đối xử.",
                "FR": "Traitez tout le monde sans discrimination.",
                "NE": "सबैलाई भेदभाव नगरी व्यवहार गर्नुहोस्।",
                "BN": "বৈষম্য ছাড়াই সকলের সাথে আচরণ করুন।",
                "ZH": "对待所有人不得歧视。",
                "KO": "모두를 차별없이 취급합니다.",
                "TL": "Tratuhin ang lahat nang walang diskriminasyon.",
                "MY": "လူတိုင်းကို ခွဲခြားဆက်ဆံခြင်းမရှိဘဲ ဆက်ဆံပါ။",
                "HI": "सभी के साथ बिना भेदभाव के व्यवहार करें।",
                "AR": "تعامل مع الجميع دون تمييز.",
                "FA": "با همه بدون تبعیض رفتار کنید."
            }
        }
    ],
    "meanings_translations": [
        {
            "ID": "diskriminasi",
            "ES": "discriminación",
            "VI": "phân biệt",
            "FR": "discrimination",
            "NE": "भेदभाव",
            "BN": "বৈষম্য",
            "ZH": "歧视",
            "KO": "차별",
            "TL": "diskriminasyon",
            "MY": "ခွဲခြားဆက်ဆံမှု",
            "HI": "भेदभाव",
            "AR": "تمييز",
            "FA": "تبعیض",
            "EN": [
                "discrimination",
                "prejudice",
                "bias",
                "segregation",
                "inequity"
            ]
        },
        {
            "ID": "perbedaan",
            "ES": "distinción",
            "VI": "sự phân biệt",
            "FR": "distinction",
            "NE": "भिन्नता",
            "BN": "পার্থক্য",
            "ZH": "区别",
            "KO": "구별",
            "TL": "pagkakaiba",
            "MY": "ထူးခြားချက်",
            "HI": "भेद",
            "AR": "امتياز",
            "FA": "تمایز",
            "EN": [
                "distinction",
                "differentiation",
                "classification"
            ]
        }
    ],
    "jisho_data": {
        "slug": "差別",
        "is_common": true,
        "tags": [
            "wanikani24",
            "wanikani26"
        ],
        "jlpt": [
            "jlpt-n3"
        ],
        "japanese": [
            {
                "word": "差別",
                "reading": "さべつ"
            },
            {
                "word": "差別",
                "reading": "しゃべつ"
            },
            {
                "word": "差別",
                "reading": "しゃべち"
            }
        ],
        "senses": [
            {
                "english_definitions": [
                    "distinction",
                    "differentiation",
                    "discrimination"
                ],
                "parts_of_speech": [
                    "Noun",
                    "Suru verb",
                    "Transitive verb"
                ],
                "links": [],
                "tags": [],
                "restrictions": [],
                "see_also": [],
                "antonyms": [],
                "source": [],
                "info": []
            },
            {
                "english_definitions": [
                    "discrimination (against people)"
                ],
                "parts_of_speech": [
                    "Noun",
                    "Suru verb",
                    "Transitive verb"
                ],
                "links": [],
                "tags": [],
                "restrictions": [],
                "see_also": [],
                "antonyms": [],
                "source": [],
                "info": []
            },
            {
                "english_definitions": [
                    "Discrimination"
                ],
                "parts_of_speech": [
                    "Wikipedia definition"
                ],
                "links": [
                    {
                        "text": "Read “Discrimination” on English Wikipedia",
                        "url": "http://en.wikipedia.org/wiki/Discrimination?oldid=495244749"
                    },
                    {
                        "text": "Read “差別” on Japanese Wikipedia",
                        "url": "http://ja.wikipedia.org/wiki/差別?oldid=41912038"
                    }
                ],
                "tags": [],
                "restrictions": [],
                "see_also": [],
                "antonyms": [],
                "source": [],
                "info": [],
                "sentences": []
            }
        ],
        "attribution": {
            "jmdict": true,
            "jmnedict": false,
            "dbpedia": "http://dbpedia.org/resource/Discrimination"
        }
    },
    "kanji_list": [
        "差",
        "別"
    ],
    "kanji_data": {
        "差": {
            "freq_mainichi_shinbun": 449,
            "grade": 4,
            "heisig_en": "distinction",
            "jlpt": 3,
            "kanji": "差",
            "kun_readings": [
                "さ.し",
                "さ.す"
            ],
            "meanings": [
                "balance",
                "difference",
                "discrepancy",
                "distinction",
                "margin",
                "variation"
            ],
            "name_readings": [],
            "notes": [],
            "on_readings": [
                "サ"
            ],
            "stroke_count": 10,
            "unicode": "5DEE"
        },
        "別": {
            "freq_mainichi_shinbun": 214,
            "grade": 4,
            "heisig_en": "separate",
            "jlpt": 4,
            "kanji": "別",
            "kun_readings": [
                "わ.ける",
                "わか.れる"
            ],
            "meanings": [
                "another",
                "branch off",
                "diverge",
                "extra",
                "fork",
                "separate",
                "specially"
            ],
            "name_readings": [
                "べっ"
            ],
            "notes": [],
            "on_readings": [
                "ベツ"
            ],
            "stroke_count": 7,
            "unicode": "5225"
        }
    }
}