{
    "version": "0.3.0",
    "word": "暴れる",
    "jlpt_level": 2,
    "youtube_link": "https://youtu.be/ISaRMMHDiGc",
    "in_db": true,
    "kanji": "暴れる",
    "reading": "あばれる",
    "introduction_japanese": "暴れる。子どもが泣いて手足を大きく動かすときや、酔った人がさわぐときに使います。",
    "introduction_english": "あばれる. We use this when a child cries and flails around, or when a drunk person makes a scene.",
    "meanings": [
        [
            "rampage",
            "riot",
            "rage"
        ],
        [
            "struggle",
            "thrash",
            "flail"
        ],
        [
            "misbehave",
            "act"
        ]
    ],
    "meaning_explanation_japanese": "力いっぱい乱暴に動くことです。人や動物が手足をふりまわしたり、ものをこわしそうにしたりする感じです。",
    "meaning_explanation_english": "It is an intransitive ru-verb (ichidan). あばれる means to move or behave violently, like to rampage or struggle, often with wild body movement or loss of control.",
    "youtube_description": "Learn how to use あばれる: meanings, easy examples, and everyday collocations. Short, clear, beginner-friendly Japanese.",
    "kanji_details": [
        {
            "kanji": "暴",
            "onyomi": [
                "ボウ",
                "バク"
            ],
            "kunyomi": [
                "あば-れる",
                "あば-く"
            ],
            "meanings_english": [
                "violent",
                "outburst",
                "rage"
            ],
            "common_words": [
                "暴力（ぼうりょく）: violence",
                "暴走（ぼうそう）: reckless driving; rampage"
            ]
        }
    ],
    "kanji_explanation": "The only kanji means violent force and sudden outburst. You see it in ぼうりょく and ぼうそう. It often carries a rough, out-of-control feeling. Think of power bursting out all at once.",
    "synonyms": [
        "荒れる : あれる : get rough; be wild",
        "騒ぐ : さわぐ : make a racket; make a fuss"
    ],
    "synonym_explanation": "The most common synonyms of the word are あれる and さわぐ. あれる overlaps when things get rough or wild, and さわぐ overlaps when people make loud, restless noise. あばれる is stronger and more physical, with wilder movement.",
    "antonyms": [
        "落ち着く : おちつく : calm down",
        "静まる : しずまる : become quiet"
    ],
    "antonym_explanation": "The most common antonyms of the word are おちつく and しずまる. These show calming or quieting down, the opposite of wild, out-of-control movement in あばれる.",
    "collocations": [
        {
            "kanji": "暴れる子ども",
            "furigana": "暴(あば)れる子(こ)ども",
            "translations": {
                "EN": "violent children",
                "ID": "anak-anak yang melakukan kekerasan",
                "ES": "niños violentos",
                "VI": "trẻ em bạo lực",
                "FR": "enfants violents",
                "NE": "हिंस्रक बालबालिकाहरू",
                "BN": "হিংস্র শিশুরা",
                "ZH": "暴力儿童",
                "KO": "날뛰는 아이",
                "TL": "marahas na mga bata",
                "MY": "ကြမ်းတမ်းသောကလေးများ",
                "HI": "हिंसक बच्चे",
                "AR": "الأطفال العنيفون",
                "FA": "کودکان خشونت آمیز"
            }
        },
        {
            "kanji": "暴れる犬",
            "furigana": "暴(あば)れる犬(いぬ)",
            "translations": {
                "EN": "Raging dog",
                "ID": "Anjing yang mengamuk",
                "ES": "perro furioso",
                "VI": "Chó dữ",
                "FR": "Chien enragé",
                "NE": "रिसाएको कुकुर",
                "BN": "রাগী কুকুর",
                "ZH": "狂犬",
                "KO": "날뛰는 개",
                "TL": "Nagngangalit na aso",
                "MY": "ခွေးရူး",
                "HI": "उग्र कुत्ता",
                "AR": "كلب هائج",
                "FA": "سگ خشمگین"
            }
        },
        {
            "kanji": "暴れる馬",
            "furigana": "暴(あば)れる馬(うま)",
            "translations": {
                "EN": "Raging Horse",
                "ID": "Kuda Mengamuk",
                "ES": "Caballo furioso",
                "VI": "Ngựa nổi giận",
                "FR": "Cheval enragé",
                "NE": "रिसाउने घोडा",
                "BN": "রাগিং হর্স",
                "ZH": "狂怒之马",
                "KO": "날뛰는 말",
                "TL": "Nagngangalit na Kabayo",
                "MY": "Raging Horse",
                "HI": "उग्र घोड़ा",
                "AR": "الحصان الهائج",
                "FA": "اسب خشمگین"
            }
        },
        {
            "kanji": "暴れる患者",
            "furigana": "暴(あば)れる患者(かんじゃ)",
            "translations": {
                "EN": "violent patient",
                "ID": "pasien yang melakukan kekerasan",
                "ES": "paciente violento",
                "VI": "bệnh nhân hung dữ",
                "FR": "patient violent",
                "NE": "हिंस्रक बिरामी",
                "BN": "হিংস্র রোগী",
                "ZH": "暴力病人",
                "KO": "날뛰는 환자",
                "TL": "marahas na pasyente",
                "MY": "ကြမ်းတမ်းသောလူနာ",
                "HI": "हिंसक रोगी",
                "AR": "مريض عنيف",
                "FA": "بیمار خشن"
            }
        },
        {
            "kanji": "酔った人が暴れる",
            "furigana": "酔(よ)った人(ひと)が暴(あば)れる",
            "translations": {
                "EN": "Drunk people become violent",
                "ID": "Orang mabuk menjadi kasar",
                "ES": "Los borrachos se vuelven violentos",
                "VI": "Người say rượu trở nên hung bạo",
                "FR": "Les personnes ivres deviennent violentes",
                "NE": "मातेका मानिसहरू हिंस्रक हुन्छन्",
                "BN": "মাতাল মানুষ হিংস্র হয়ে ওঠে",
                "ZH": "醉酒者会变得暴力",
                "KO": "술취한 사람이 날뛰다",
                "TL": "Ang mga taong lasing ay nagiging marahas",
                "MY": "အရက်မူးတဲ့လူတွေက ကြမ်းတယ်။",
                "HI": "नशे में लोग हिंसक हो जाते हैं",
                "AR": "يصبح الأشخاص السكارى عنيفين",
                "FA": "افراد مست خشن می‌شوند"
            }
        },
        {
            "kanji": "教室で暴れる",
            "furigana": "教室(きょうしつ)で暴(あば)れる",
            "translations": {
                "EN": "Rampage in the classroom",
                "ID": "Amukan di dalam kelas",
                "ES": "Descontrol en el aula",
                "VI": "Sự hung hăng trong lớp học",
                "FR": "Déchaînement dans la salle de classe",
                "NE": "कक्षाकोठामा हूलदङ्गा",
                "BN": "শ্রেণীকক্ষে তাণ্ডব",
                "ZH": "教室里的暴乱",
                "KO": "교실에서 날뛰다",
                "TL": "Rampage sa classroom",
                "MY": "စာသင်ခန်းထဲမှာ သောင်းကျန်းတယ်။",
                "HI": "कक्षा में उत्पात",
                "AR": "هياج في الفصل الدراسي",
                "FA": "آشوب در کلاس درس"
            }
        },
        {
            "kanji": "店で暴れる",
            "furigana": "店(みせ)で暴(あば)れる",
            "translations": {
                "EN": "Violent behavior in the store",
                "ID": "Perilaku kekerasan di toko",
                "ES": "Comportamiento violento en la tienda",
                "VI": "Hành vi bạo lực trong cửa hàng",
                "FR": "Comportements violents dans le magasin",
                "NE": "पसलमा हिंसात्मक व्यवहार",
                "BN": "দোকানে হিংসাত্মক আচরণ",
                "ZH": "商店内的暴力行为",
                "KO": "가게에서 날뛰다",
                "TL": "Marahas na pag-uugali sa tindahan",
                "MY": "ဆိုင်အတွင်း ကြမ်းတမ်းသော အပြုအမူ",
                "HI": "दुकान में हिंसक व्यवहार",
                "AR": "سلوك عنيف في المتجر",
                "FA": "رفتار خشونت‌آمیز در فروشگاه"
            }
        },
        {
            "kanji": "大声で暴れる",
            "furigana": "大(おお)声(ごえ)で暴(あば)れる},{",
            "translations": {
                "EN": "shouting and raging",
                "ID": "berteriak dan mengamuk",
                "ES": "gritos y furia",
                "VI": "la hét và giận dữ",
                "FR": "cris et rage",
                "NE": "चिच्याउने र रिसाउने",
                "BN": "চিৎকার এবং ক্রোধ",
                "ZH": "叫喊和咆哮",
                "KO": "큰 소리로 날뛰다",
                "TL": "sumisigaw at nagngangalit",
                "MY": "အော်ဟစ်၍ အော်ဟစ်ခြင်း၊",
                "HI": "चिल्लाना और गुस्सा करना",
                "AR": "الصراخ والهياج",
                "FA": "فریاد زدن و خشمگین شدن"
            }
        }
    ],
    "example_sentences": [
        {
            "kanji": "子どもが泣いて暴れました。",
            "furigana": "子(こ)どもが泣(な)いて暴(あば)れました。",
            "translations": {
                "EN": "The child cried and became violent.",
                "ID": "Anak itu menangis dan menjadi kasar.",
                "ES": "El niño lloró y se puso violento.",
                "VI": "Đứa trẻ khóc và trở nên hung dữ.",
                "FR": "L'enfant a pleuré et est devenu violent.",
                "NE": "बच्चा रोयो र हिंस्रक भयो।",
                "BN": "শিশুটি কেঁদে উঠল এবং হিংস্র হয়ে উঠল।",
                "ZH": "孩子哭闹起来，变得暴力起来。",
                "KO": "아이가 울고 날뛰었습니다.",
                "TL": "Ang bata ay umiyak at naging marahas.",
                "MY": "ကလေးက ငိုပြီး ရက်စက်တယ်။",
                "HI": "बच्चा रोया और हिंसक हो गया।",
                "AR": "بكى الطفل وأصبح عنيفًا.",
                "FA": "کودک گریه کرد و پرخاشگر شد."
            }
        },
        {
            "kanji": "馬が急に暴れた。",
            "furigana": "馬(うま)が急(きゅう)に暴(あば)れた。",
            "translations": {
                "EN": "The horse suddenly became violent.",
                "ID": "Kuda itu tiba-tiba menjadi ganas.",
                "ES": "El caballo se volvió violento de repente.",
                "VI": "Con ngựa đột nhiên trở nên hung dữ.",
                "FR": "Le cheval devint soudainement violent.",
                "NE": "घोडा अचानक हिंस्रक भयो।",
                "BN": "ঘোড়াটি হঠাৎ হিংস্র হয়ে উঠল।",
                "ZH": "马突然变得狂躁起来。",
                "KO": "말이 갑자기 날뛰었다.",
                "TL": "Biglang naging marahas ang kabayo.",
                "MY": "မြင်းသည် ရုတ်တရက် ကြမ်းတမ်းလာသည်။",
                "HI": "घोड़ा अचानक हिंसक हो गया।",
                "AR": "فجأة أصبح الحصان عنيفًا.",
                "FA": "اسب ناگهان خشن شد."
            }
        },
        {
            "kanji": "兄は酔って店で暴れました。",
            "furigana": "兄(あに)は酔(よ)って店(みせ)で暴(あば)れました。",
            "translations": {
                "EN": "My brother got drunk and caused a disturbance in the store.",
                "ID": "Kakakku mabuk dan membuat keributan di toko.",
                "ES": "Mi hermano se emborrachó y provocó un altercado en la tienda.",
                "VI": "Anh trai tôi say rượu và gây náo loạn trong cửa hàng.",
                "FR": "Mon frère s'est enivré et a provoqué un trouble dans le magasin.",
                "NE": "मेरो भाइ रक्सीले मातेर पसलमा हंगामा मच्चायो।",
                "BN": "আমার ভাই মাতাল হয়ে দোকানে গোলমাল সৃষ্টি করেছিল।",
                "ZH": "我哥哥喝醉了，在店里闹事。",
                "KO": "형은 취해서 가게에서 날뛰었습니다.",
                "TL": "Nalasing ang kapatid ko at nagkagulo sa tindahan.",
                "MY": "အစ်ကိုက အရက်မူးပြီး စတိုးဆိုင်မှာ အနှောင့်အယှက်ဖြစ်ခဲ့တယ်။",
                "HI": "मेरा भाई नशे में धुत होकर दुकान में हंगामा करने लगा।",
                "AR": "لقد سكر أخي وتسبب في حدوث اضطرابات في المتجر.",
                "FA": "برادرم مست کرد و در فروشگاه آشوب به پا کرد."
            }
        },
        {
            "kanji": "犬が注射で暴れました。",
            "furigana": "犬(いぬ)が注射(ちゅうしゃ)で暴(あば)れました。",
            "translations": {
                "EN": "My dog got violent after getting the injection.",
                "ID": "Anjing saya menjadi kasar setelah disuntik.",
                "ES": "Mi perro se puso agresivo después de recibir la inyección.",
                "VI": "Chó của tôi trở nên hung dữ sau khi tiêm.",
                "FR": "Mon chien est devenu violent après avoir reçu l'injection.",
                "NE": "सुई लगाएपछि मेरो कुकुर हिंस्रक भयो।",
                "BN": "ইনজেকশন দেওয়ার পর আমার কুকুরটি হিংস্র হয়ে ওঠে।",
                "ZH": "我的狗打完针后变得很暴躁。",
                "KO": "개가 주사로 날뛰었습니다.",
                "TL": "Ang aking aso ay naging marahas pagkatapos ma-iniksyon.",
                "MY": "ဆေးထိုးပြီးရင် ခွေးက ရက်စက်တယ်။",
                "HI": "इंजेक्शन लगने के बाद मेरा कुत्ता हिंसक हो गया।",
                "AR": "لقد أصبح كلبي عنيفًا بعد الحصول على الحقنة.",
                "FA": "سگ من بعد از تزریق، رفتار خشونت‌آمیزی از خود نشان داد."
            }
        },
        {
            "kanji": "彼は怒って部屋で暴れています。",
            "furigana": "彼(かれ)は怒(おこ)って部屋(へや)で暴(あば)れています。",
            "translations": {
                "EN": "He is angry and storming around the room.",
                "ID": "Dia marah dan mengamuk di sekitar ruangan.",
                "ES": "Está furioso y da vueltas por la habitación.",
                "VI": "Anh ta tức giận và đi vòng quanh phòng.",
                "FR": "Il est en colère et arpente la pièce en trombe.",
                "NE": "ऊ रिसाएको छ र कोठाभरि होहल्ला मच्चाइरहेको छ।",
                "BN": "সে রেগে আছে এবং ঘরের মধ্যে ঝড় তুলেছে।",
                "ZH": "他很生气，在房间里来回踱步。",
                "KO": "그는 화가 나서 방에서 날뛰고 있습니다.",
                "TL": "Siya ay galit at storming sa paligid ng silid.",
                "MY": "ဒေါသတကြီးနဲ့ အခန်းထဲကို လှည့်ပတ်နေတယ်။",
                "HI": "वह गुस्से में है और कमरे में इधर-उधर घूम रहा है।",
                "AR": "إنه غاضب ويتجول في الغرفة.",
                "FA": "او عصبانی است و در اتاق داد و بیداد می‌کند."
            }
        }
    ],
    "meanings_translations": [
        {
            "ID": "mengamuk",
            "ES": "alboroto",
            "VI": "hung hăng",
            "FR": "carnage",
            "NE": "उग्रवाद",
            "BN": "তাণ্ডব",
            "ZH": "横冲直撞",
            "KO": "난동",
            "TL": "magalit nang labis",
            "MY": "သောင်းကျန်းသည်။",
            "HI": "क्रोध",
            "AR": "الهياج",
            "FA": "داد و بیداد",
            "EN": [
                "rampage",
                "riot",
                "rage"
            ]
        },
        {
            "ID": "berjuang",
            "ES": "lucha",
            "VI": "đấu tranh ",
            "FR": "lutte",
            "NE": "संघर्ष गर्नु",
            "BN": "সংগ্রাম",
            "ZH": "斗争",
            "KO": "고심하다",
            "TL": "pakikibaka",
            "MY": "ရုန်းကန်",
            "HI": "संघर्ष",
            "AR": "كفاح",
            "FA": "مبارزه",
            "EN": [
                "struggle",
                "thrash",
                "flail"
            ]
        },
        {
            "ID": "berbuat jahat",
            "ES": "portarse mal",
            "VI": "cư xử không đúng mực",
            "FR": "se conduire mal",
            "NE": "दुर्व्यवहार गर्नु",
            "BN": "খারাপ ব্যবহার করা",
            "ZH": "行为不端",
            "KO": "나쁜 짓을 하다",
            "TL": "maling kumilos",
            "MY": "အကျင့်ဆိုး",
            "HI": "दुर्व्यवहार",
            "AR": "سوء التصرف",
            "FA": "بدرفتاری کردن",
            "EN": [
                "misbehave",
                "act"
            ]
        }
    ],
    "jisho_data": {
        "slug": "暴れる",
        "is_common": true,
        "tags": [
            "wanikani19"
        ],
        "jlpt": [
            "jlpt-n2"
        ],
        "japanese": [
            {
                "word": "暴れる",
                "reading": "あばれる"
            }
        ],
        "senses": [
            {
                "english_definitions": [
                    "to act violently",
                    "to rage",
                    "to struggle",
                    "to be riotous"
                ],
                "parts_of_speech": [
                    "Ichidan verb",
                    "Intransitive verb"
                ],
                "links": [],
                "tags": [],
                "restrictions": [],
                "see_also": [],
                "antonyms": [],
                "source": [],
                "info": []
            }
        ],
        "attribution": {
            "jmdict": true,
            "jmnedict": false,
            "dbpedia": false
        }
    },
    "kanji_list": [
        "暴"
    ],
    "kanji_data": {
        "暴": {
            "freq_mainichi_shinbun": 692,
            "grade": 5,
            "heisig_en": "outburst",
            "jlpt": 2,
            "kanji": "暴",
            "kun_readings": [
                "あば.く",
                "あば.れる"
            ],
            "meanings": [
                "cruelty",
                "force",
                "fret",
                "outburst",
                "outrage",
                "rave",
                "violence"
            ],
            "name_readings": [],
            "notes": [],
            "on_readings": [
                "バク",
                "ボウ"
            ],
            "stroke_count": 15,
            "unicode": "66B4"
        }
    }
}