{
  "version": "0.3.0",
  "word": "隠す",
  "jlpt_level": 3,
  "youtube_link": "https://youtu.be/EqzyBG6lIaw",
  "in_db": true,
  "kanji": "隠す",
  "reading": "かくす",
  "introduction_japanese": "隠すは、物や情報を人から見えないようにする場面、感情や本音を見せたくない時、欠点や財産を内緒にする状況などでよく使われる動詞です。",
  "introduction_english": "The verb かくす is commonly used when talking about making things or information not visible to others, not showing feelings or true intentions, or keeping flaws or assets private.",
  "meanings": [
    [
      "to hide (physically) something from sight",
      "to conceal an object or fact"
    ],
    [
      "to hide (emotion, intention, flaw)",
      "to keep something secret or not show true feelings"
    ]
  ],
  "meaning_explanation_japanese": "「かくす」は、物や事実を人の目から見えないようにすること、または感情や考えを表に出さないで内にしまっておくことを表す言葉です。",
  "meaning_explanation_english": "The word かくす means to hide or conceal something. It can refer to hiding physical things or hiding feelings, intentions, or facts.",
  "youtube_description": "",
  "kanji_details": [
    {
      "kanji": "隠",
      "common_words": [
        "隠れる (かくれる): to hide (intransitive), to take shelter",
        "隠し事 (かくしごと): a secret; something kept hidden"
      ]
    }
  ],
  "kanji_explanation": "The first kanji means conceal or hide. It appears in words like かくれる and かくしごと. In かくれる it keeps the sense of someone or something moving out of sight and in かくしごと it gives the idea of something kept secret.",
  "synonyms": [
    "隠蔽する : いんぺいする : to conceal, to cover up (formal)"
  ],
  "synonym_explanation": "The most common synonym of the かくす is いんぺいする. いんぺいする is more formal and often used in legal or official contexts to mean covering up or concealing information.",
  "antonyms": [
    "見せる : みせる : to show, to display"
  ],
  "antonym_explanation": "The most common antonym of the かくす is みせる. みせる means to show or reveal, which is the opposite action of hiding.",
  "collocations": [
    {
      "kanji": "真実を隠す",
      "furigana": "真実を隠す",
      "translations": {}
    },
    {
      "kanji": "秘密を隠す",
      "furigana": "秘密を隠す",
      "translations": {}
    },
    {
      "kanji": "欠点を隠す",
      "furigana": "欠点を隠す",
      "translations": {}
    },
    {
      "kanji": "本音を隠す",
      "furigana": "本音を隠す",
      "translations": {}
    },
    {
      "kanji": "財産を隠す",
      "furigana": "財産を隠す",
      "translations": {}
    },
    {
      "kanji": "影で隠して",
      "furigana": "影で隠して",
      "translations": {}
    },
    {
      "kanji": "声を隠して",
      "furigana": "声を隠して",
      "translations": {}
    },
    {
      "kanji": "身を隠して",
      "furigana": "身を隠して",
      "translations": {}
    },
    {
      "kanji": "顔を隠して",
      "furigana": "顔を隠して",
      "translations": {}
    },
    {
      "kanji": "本当の意図を隠して",
      "furigana": "本当の意図を隠して",
      "translations": {}
    },
    {
      "kanji": "意図を隠す",
      "furigana": "意図を隠す",
      "translations": {}
    },
    {
      "kanji": "感情を隠す",
      "furigana": "感情を隠す",
      "translations": {}
    },
    {
      "kanji": "事実を隠す",
      "furigana": "事実を隠す",
      "translations": {}
    },
    {
      "kanji": "痛みを隠す",
      "furigana": "痛みを隠す",
      "translations": {}
    },
    {
      "kanji": "弱みを隠す",
      "furigana": "弱みを隠す",
      "translations": {}
    },
    {
      "kanji": "こっそり隠す",
      "furigana": "こっそり隠す",
      "translations": {}
    },
    {
      "kanji": "完全に隠す",
      "furigana": "完全に隠す",
      "translations": {}
    },
    {
      "kanji": "うまく隠す",
      "furigana": "うまく隠す",
      "translations": {}
    },
    {
      "kanji": "巧妙に隠す",
      "furigana": "巧妙に隠す",
      "translations": {}
    },
    {
      "kanji": "密かに隠す",
      "furigana": "密かに隠す",
      "translations": {}
    }
  ],
  "example_sentences": [
    {
      "kanji": "真実を隠す。",
      "furigana": "真実(しんじつ)を隠す(かくす)。",
      "translations": {
        "EN": "Hide the truth.",
        "ID": "Sembunyikan kebenaran.",
        "ES": "Ocultar la verdad.",
        "VI": "Che giấu sự thật.",
        "FR": "Cacher la vérité.",
        "NE": "सत्य लुकाउनुहोस्।",
        "BN": "সত্য লুকাও।",
        "ZH": "隐瞒真相。",
        "KO": "진실을 숨긴다.",
        "TL": "Itago ang katotohanan.",
        "MY": "အမှန်တရားကို ဖုံးကွယ်ပါ။",
        "HI": "सच छुपाओ.",
        "AR": "إخفاء الحقيقة",
        "FA": "حقیقت را پنهان کنید."
      }
    },
    {
      "kanji": "秘密を隠している。",
      "furigana": "秘密(ひみつ)を隠して(かくして)いる。",
      "translations": {
        "EN": "He is hiding a secret.",
        "ID": "Dia menyembunyikan suatu rahasia.",
        "ES": "Él está ocultando un secreto.",
        "VI": "Anh ấy đang che giấu một bí mật.",
        "FR": "Il cache un secret.",
        "NE": "उसले एउटा रहस्य लुकाइरहेको छ।",
        "BN": "সে একটা গোপন কথা লুকাচ্ছে।",
        "ZH": "他隐藏了一个秘密。",
        "KO": "비밀을 숨기고 있다.",
        "TL": "May tinatago siyang sikreto.",
        "MY": "သူက လျှို့ဝှက်ချက်တစ်ခုပေါ့။",
        "HI": "वह एक रहस्य छुपा रहा है.",
        "AR": "إنه يخفي سرًا.",
        "FA": "او رازی را پنهان می‌کند."
      }
    },
    {
      "kanji": "感情を隠すのは難しい。",
      "furigana": "感情(かんじょう)を隠す(かくす)のは難(むずか)しい。",
      "translations": {
        "EN": "It's hard to hide your emotions.",
        "ID": "Sulit untuk menyembunyikan emosi Anda.",
        "ES": "Es difícil ocultar tus emociones.",
        "VI": "Thật khó để che giấu cảm xúc của bạn.",
        "FR": "Il est difficile de cacher ses émotions.",
        "NE": "आफ्ना भावनाहरू लुकाउन गाह्रो छ।",
        "BN": "নিজের আবেগ লুকানো কঠিন।",
        "ZH": "隐藏自己的情绪是件很难的事。",
        "KO": "감정을 숨기는 것은 어렵다.",
        "TL": "Mahirap itago ang iyong emosyon.",
        "MY": "မင်းရဲ့ခံစားချက်တွေကို ဖုံးကွယ်ဖို့ခက်တယ်။",
        "HI": "अपनी भावनाओं को छिपाना कठिन है।",
        "AR": "من الصعب إخفاء مشاعرك.",
        "FA": "پنهان کردن احساساتت سخته."
      }
    },
    {
      "kanji": "顔を隠して出かけた。",
      "furigana": "顔(かお)を隠して(かくして)出(で)かけた。",
      "translations": {
        "EN": "I went out hiding my face.",
        "ID": "Aku keluar sambil menyembunyikan wajahku.",
        "ES": "Salí escondiendo mi cara.",
        "VI": "Tôi đi ra ngoài và che mặt.",
        "FR": "Je suis sorti en cachant mon visage.",
        "NE": "म अनुहार लुकाएर बाहिर निस्किएँ।",
        "BN": "আমি মুখ লুকিয়ে বাইরে চলে গেলাম।",
        "ZH": "我躲着脸出去了。",
        "KO": "얼굴을 숨기고 나갔다.",
        "TL": "Lumabas ako na tinatago ang mukha ko.",
        "MY": "မျက်နှာကို ကွယ်ပြီး ထွက်သွားခဲ့တယ်။",
        "HI": "मैं अपना चेहरा छुपाते हुए बाहर चला गया।",
        "AR": "خرجت وأخفيت وجهي.",
        "FA": "رفتم بیرون و صورتم را پنهان کردم."
      }
    },
    {
      "kanji": "痛みを隠さないで話して。",
      "furigana": "痛(いた)みを隠さ(かくさ)ないで話(はな)して。",
      "translations": {
        "EN": "Don't hide your pain, talk about it.",
        "ID": "Jangan sembunyikan rasa sakitmu, bicarakanlah.",
        "ES": "No escondas tu dolor, habla de él.",
        "VI": "Đừng che giấu nỗi đau của bạn, hãy nói ra.",
        "FR": "Ne cachez pas votre douleur, parlez-en.",
        "NE": "आफ्नो पीडा लुकाउन नखोज, त्यसको बारेमा कुरा गर।",
        "BN": "তোমার কষ্ট লুকাও না, কথা বলো।",
        "ZH": "不要隐藏你的痛苦，谈论它。",
        "KO": "고통을 숨기지 말고.",
        "TL": "Huwag itago ang iyong sakit, pag-usapan ito.",
        "MY": "မင်းရဲ့နာကျင်မှုကို ဖုံးကွယ်မထားပါနဲ့၊ အဲဒါကို ပြောပြပါ။",
        "HI": "अपना दर्द छिपाएं नहीं, इसके बारे में बात करें।",
        "AR": "لا تخفي ألمك، تحدث عنه.",
        "FA": "دردت را پنهان نکن، در موردش صحبت کن."
      }
    },
    {
      "kanji": "財産を隠すのは良くない。",
      "furigana": "財産(ざいさん)を隠す(かくす)のは良(よ)くない。",
      "translations": {
        "EN": "It's not good to hide your assets.",
        "ID": "Tidak baik menyembunyikan aset Anda.",
        "ES": "No es bueno ocultar tus activos.",
        "VI": "Việc che giấu tài sản của bạn là không tốt.",
        "FR": "Il n’est pas bon de cacher ses biens.",
        "NE": "आफ्नो सम्पत्ति लुकाउनु राम्रो होइन।",
        "BN": "তোমার সম্পদ গোপন করা ভালো নয়।",
        "ZH": "隐藏资产是不好的。",
        "KO": "재산을 숨기는 것은 좋지 않다.",
        "TL": "Hindi magandang itago ang iyong mga ari-arian.",
        "MY": "သင့်ပိုင်ဆိုင်မှုများကို ဖုံးကွယ်ထားရန် မကောင်းပါ။",
        "HI": "अपनी संपत्ति छिपाना अच्छा नहीं है।",
        "AR": "ليس من الجيد إخفاء أصولك.",
        "FA": "پنهان کردن دارایی‌ها کار درستی نیست."
      }
    }
  ],
  "meanings_translations": {
    "to hide (physically) something from sight": {
      "ID": "menyembunyikan (secara fisik) sesuatu dari pandangan",
      "ES": "ocultar (físicamente) algo de la vista",
      "VI": "giấu (về mặt vật lý) một cái gì đó khỏi tầm nhìn",
      "FR": "cacher (physiquement) quelque chose à la vue",
      "NE": "(शारीरिक रूपमा) कुनै कुरालाई नजरबाट लुकाउनु",
      "BN": "(শারীরিকভাবে) দৃষ্টির আড়ালে কিছু লুকানো",
      "ZH": "（物理上）隐藏某物",
      "KO": "(물리적으로) 무언가를 시야에서 숨기다",
      "TL": "upang itago (pisikal) ang isang bagay mula sa paningin",
      "MY": "(ရုပ်ပိုင်းဆိုင်ရာ) တစ်ခုခုကို မျက်စိမှိတ်ဖုံးကွယ်ရန်",
      "HI": "किसी चीज़ को (शारीरिक रूप से) दृष्टि से छिपाना",
      "AR": "إخفاء شيء ما (جسديًا) عن الأنظار",
      "FA": "چیزی را (از نظر فیزیکی) از دید پنهان کردن",
      "EN": [
        "to conceal an object or fact"
      ]
    },
    "to hide (emotion, intention, flaw)": {
      "ID": "menyembunyikan (emosi, niat, kekurangan)",
      "ES": "ocultar (emoción, intención, defecto)",
      "VI": "che giấu (cảm xúc, ý định, khuyết điểm)",
      "FR": "cacher (émotion, intention, défaut)",
      "NE": "लुकाउनु (भावना, मनसाय, त्रुटि)",
      "BN": "(আবেগ, উদ্দেশ্য, ত্রুটি) লুকানো",
      "ZH": "隐藏（情感、意图、缺陷）",
      "KO": "(감정, 의도, 결점을) 숨기다",
      "TL": "itago (emosyon, intensyon, kapintasan)",
      "MY": "ဖျောက်ရန် (စိတ်ခံစားမှု၊ ရည်ရွယ်ချက်၊ ချို့ယွင်းချက်)",
      "HI": "(भावना, इरादा, दोष) छिपाना",
      "AR": "إخفاء (العاطفة، النية، العيب)",
      "FA": "پنهان کردن (احساس، نیت، نقص)",
      "EN": [
        "to keep something secret or not show true feelings"
      ]
    }
  },
  "jisho_data": {
    "slug": "隠す",
    "is_common": true,
    "tags": [
      "wanikani25"
    ],
    "jlpt": [
      "jlpt-n3"
    ],
    "japanese": [
      {
        "word": "隠す",
        "reading": "かくす"
      },
      {
        "word": "匿す",
        "reading": "かくす"
      }
    ],
    "senses": [
      {
        "english_definitions": [
          "to hide",
          "to conceal"
        ],
        "parts_of_speech": [
          "Godan verb with 'su' ending",
          "Transitive verb"
        ],
        "links": [],
        "tags": [],
        "restrictions": [],
        "see_also": [],
        "antonyms": [],
        "source": [],
        "info": []
      }
    ],
    "attribution": {
      "jmdict": true,
      "jmnedict": false,
      "dbpedia": false
    }
  },
  "kanji_list": [
    "隠"
  ],
  "kanji_data": {
    "隠": {
      "freq_mainichi_shinbun": 1089,
      "grade": 8,
      "heisig_en": "conceal",
      "jlpt": 1,
      "kanji": "隠",
      "kun_readings": [
        "かく.し",
        "かく.す",
        "かく.れる",
        "よ.る"
      ],
      "meanings": [
        "conceal",
        "cover",
        "hide"
      ],
      "name_readings": [
        "お",
        "がくし"
      ],
      "notes": [],
      "on_readings": [
        "イン",
        "オン"
      ],
      "stroke_count": 14,
      "unicode": "96A0"
    }
  }
}